<define>
    <constant name="world_side" value="600.*m"/>
    <constant name="world_x" value="world_side"/>
    <constant name="world_y" value="world_side"/>
    <constant name="world_z" value="world_side"/>


    <constant name="tracker_region_rmax" value="200.0*m"/>
    <constant name="tracker_region_zmax"   value="200.0*m"/>


    
 

    <constant name="DRcrystalwidth" value="1.0*cm"/>
<!--    <constant name="DRcrystallength" value="21.*cm"/> -->
    <constant name="DRcrystallength" value="21.*cm"/>

    
    <constant name="EcalBarrel_ID" value="1"/>





    

</define>
